pyteamup/Calendar.py
pyteamup/Event.py
pyteamup/SubCalendar.py
pyteamup/__init__.py
pyteamup/utils/__init__.py
pyteamup/utils/constants.py
pyteamup/utils/utilities.py
pyTeamUp-0.1.4a0.dist-info/LICENSE
pyTeamUp-0.1.4a0.dist-info/METADATA
pyTeamUp-0.1.4a0.dist-info/WHEEL
pyTeamUp-0.1.4a0.dist-info/top_level.txt
pyTeamUp-0.1.4a0.dist-info/RECORD
