Metadata-Version: 2.1
Name: pyTeamUp
Version: 0.1.4a0
Summary: Python wrapper for TeamUp Calendar's API
Home-page: https://github.com/DJones4822/pyTeamUp
Author: David Jones
Author-email: David.jone4822@gmail.com
License: UNKNOWN
Platform: UNKNOWN
Classifier: Programming Language :: Python :: 3
Classifier: License :: OSI Approved :: MIT License
Classifier: Operating System :: OS Independent
License-File: LICENSE
Requires-Dist: requests
Requires-Dist: datetime
Requires-Dist: python-dateutil
